encryptools/__init__.py
encryptools/decrypt_file_creator.py
encryptools/hybrid_encryptor.py
encryptools/rsa_key_manager.py
encryptools-1.2.2.dist-info/LICENSE
encryptools-1.2.2.dist-info/METADATA
encryptools-1.2.2.dist-info/WHEEL
encryptools-1.2.2.dist-info/top_level.txt
encryptools-1.2.2.dist-info/RECORD
