Metadata-Version: 2.1
Name: encryptools
Version: 1.2.2
Summary: Encrypt and Decrypt file python
Home-page: https://github.com/dioneal-farisi/encryptools
Author: Dione Alfarisi
Author-email: Dione Alfarisi <ardionefarisi1322@gmail.com>
License: MIT License
Project-URL: Home, https://github.com/dioneal-farisi/encryptools
Classifier: License :: OSI Approved :: MIT License
Requires-Python: >=3.8
License-File: LICENSE
Requires-Dist: pycryptodome
